mlpro_mpps/__init__.py
mlpro_mpps/mpps.py
mlpro_mpps/pool/__init__.py
mlpro_mpps/pool/comps/PS001_C001_Silo.py
mlpro_mpps/pool/comps/PS001_C002_Hopper.py
mlpro_mpps/pool/comps/PS001_C003_ConveyorBelt.py
mlpro_mpps/pool/comps/PS001_C004_VibratoryConveyor.py
mlpro_mpps/pool/comps/PS001_C005_RotaryFeeder.py
mlpro_mpps/pool/comps/PS001_C006_VacuumPump1.py
mlpro_mpps/pool/comps/PS001_C007_VacuumPump2.py
mlpro_mpps/pool/comps/PS001_C008_VacuumPump3.py
mlpro_mpps/pool/comps/PS001_C009_Inventory.py
mlpro_mpps/pool/comps/PS001_C010_SiloLoading.py
mlpro_mpps/pool/comps/PS002_C001_Tank.py
mlpro_mpps/pool/comps/PS002_C002_Pump1.py
mlpro_mpps/pool/comps/PS002_C003_Pump2.py
mlpro_mpps/pool/comps/PS002_C004_Pump3.py
mlpro_mpps/pool/comps/PS003_C001_Silo_17L.py
mlpro_mpps/pool/comps/PS003_C002_Hopper_9L.py
mlpro_mpps/pool/comps/PS003_C003_Silo_15L.py
mlpro_mpps/pool/comps/PS003_C004_Hopper_10L.py
mlpro_mpps/pool/comps/PS003_C005_Silo_12L.py
mlpro_mpps/pool/comps/PS003_C006_MixingSilo_17L.py
mlpro_mpps/pool/comps/PS003_C007_Hopper_8L.py
mlpro_mpps/pool/comps/PS003_C008_Silo_30L.py
mlpro_mpps/pool/comps/PS003_C009_ConveyorBelt1.py
mlpro_mpps/pool/comps/PS003_C010_ConveyorBelt2.py
mlpro_mpps/pool/comps/PS003_C011_VacuumPump1.py
mlpro_mpps/pool/comps/PS003_C012_VacuumPump2.py
mlpro_mpps/pool/comps/PS003_C013_VacuumPump3.py
mlpro_mpps/pool/comps/PS003_C014_ScrewConveyor1.py
mlpro_mpps/pool/comps/PS003_C015_ScrewConveyor2.py
mlpro_mpps/pool/comps/PS003_C016_BeltElevator1.py
mlpro_mpps/pool/comps/PS003_C017_BeltElevator2.py
mlpro_mpps/pool/comps/PS003_C018_RotaryFeeder.py
mlpro_mpps/pool/comps/PS003_C019_VibratoryConveyor.py
mlpro_mpps/pool/comps/PS003_C020_BucketElevator.py
mlpro_mpps/pool/comps/PS003_C021_DomeValve.py
mlpro_mpps/pool/comps/PS003_C022_SiloLoading.py
mlpro_mpps/pool/comps/PS003_C023_Inventory.py
mlpro_mpps/pool/comps/PS003_C024_Hopper_12L.py
mlpro_mpps/pool/comps/PS003_C025_DosingUnit.py
mlpro_mpps/pool/comps/PS003_C026_Hopper_10L_SP.py
mlpro_mpps-1.2.2.dist-info/LICENSE
mlpro_mpps-1.2.2.dist-info/METADATA
mlpro_mpps-1.2.2.dist-info/WHEEL
mlpro_mpps-1.2.2.dist-info/top_level.txt
mlpro_mpps-1.2.2.dist-info/RECORD
