Metadata-Version: 2.1
Name: mlpro-mpps
Version: 1.2.2
Summary: MLPro-MPPS - A Customizable Multi-Purpose Production System in Python
Home-page: https://mlpro.readthedocs.io
Author: MLPro Team
Author-email: mlpro@listen.fh-swf.de
Project-URL: Bug Tracker, https://mlpro.readthedocs.io
Classifier: Programming Language :: Python :: 3
Classifier: License :: OSI Approved :: Apache Software License
Classifier: Operating System :: OS Independent
Requires-Python: >=3.9
License-File: LICENSE
Provides-Extra: full
Requires-Dist: mlpro[full] >=1.3.1 ; extra == 'full'
